[
  {
    "accountID": "627286410625",
    "accountName": "bravenewt",
    "accountScope": "Linked",
    "availabilityZone": "",
    "averageNormalizedUnitsUsedPerHour": 682.98,
    "averageNumberOfInstancesUsedPerHour": 229.62,
    "averageUtilization": "7",
    "databaseEdition": "",
    "databaseEngine": "",
    "deploymentOption": "",
    "estimatedBreakEvenInMonths": "49.53",
    "estimatedMonthlyOnDemandCost": "416.24",
    "estimatedMonthlySavingsAmount": "94.02",
    "estimatedMonthlySavingsPercentage": "26",
    "estimatedReservationCostForLookbackPeriod": "11.96",
    "family": "i4i",
    "instanceClass": "",
    "instanceSize": "",
    "instanceType": "i4i.large",
    "licenseModel": "",
    "lookbackPeriodInDays": "7",
    "maximumNormalizedUnitsUsedPerHour": 78.12,
    "maximumNumberOfInstancesUsedPerHour": 25.56,
    "minimumNormalizedUnitsUsedPerHour": 57,
    "minimumNumberOfInstancesUsedPerHour": 53.36,
    "nodeType": "i4i.large",
    "paymentOption": "Partial_Upfront",
    "platform": "",
    "productDescription": "Linux/UNIX",
    "recommendedNormalizedUnitsToPurchase": "6",
    "recommendedNumberOfInstancesToPurchase": "3",
    "recurringStandardMonthlyCost": "74.49",
    "region": "Asia Pacific (Sydney)",
    "resourceType": "i4i",
    "service": "Elastic Compute Cloud (EC2)",
    "sizeFlexEligible": "false",
    "tenancy": "Shared",
    "term": "1 year",
    "upfrontCost": "32.69"
  },
  {
    "accountID": "353197488767",
    "accountName": "nervouseel",
    "accountScope": "Linked",
    "availabilityZone": "",
    "averageNormalizedUnitsUsedPerHour": 221.14,
    "averageNumberOfInstancesUsedPerHour": 292.7,
    "averageUtilization": "36",
    "databaseEdition": "",
    "databaseEngine": "",
    "deploymentOption": "",
    "estimatedBreakEvenInMonths": "94.95",
    "estimatedMonthlyOnDemandCost": "76.60",
    "estimatedMonthlySavingsAmount": "15.70",
    "estimatedMonthlySavingsPercentage": "67",
    "estimatedReservationCostForLookbackPeriod": "0.85",
    "family": "c6i",
    "instanceClass": "",
    "instanceSize": "",
    "instanceType": "c6i.large",
    "licenseModel": "",
    "lookbackPeriodInDays": "7",
    "maximumNormalizedUnitsUsedPerHour": 83.09,
    "maximumNumberOfInstancesUsedPerHour": 33.21,
    "minimumNormalizedUnitsUsedPerHour": 54.67,
    "minimumNumberOfInstancesUsedPerHour": 73.64,
    "nodeType": "c6i.large",
    "paymentOption": "Partial_Upfront",
    "platform": "",
    "productDescription": "Linux/UNIX",
    "recommendedNormalizedUnitsToPurchase": "2",
    "recommendedNumberOfInstancesToPurchase": "4",
    "recurringStandardMonthlyCost": "10.98",
    "region": "EU (Paris)",
    "resourceType": "c6i",
    "service": "Elastic Compute Cloud (EC2)",
    "sizeFlexEligible": "false",
    "tenancy": "Shared",
    "term": "1 year",
    "upfrontCost": "0.19"
  },
  {
    "accountID": "620368136857",
    "accountName": "relievedurchin",
    "accountScope": "Linked",
    "availabilityZone": "",
    "averageNormalizedUnitsUsedPerHour": 800.15,
    "averageNumberOfInstancesUsedPerHour": 369.62,
    "averageUtilization": "42",
    "databaseEdition": "",
    "databaseEngine": "",
    "deploymentOption": "",
    "estimatedBreakEvenInMonths": "49.46",
    "estimatedMonthlyOnDemandCost": "332.24",
    "estimatedMonthlySavingsAmount": "767.60",
    "estimatedMonthlySavingsPercentage": "14",
    "estimatedReservationCostForLookbackPeriod": "21.38",
    "family": "t2",
    "instanceClass": "",
    "instanceSize": "",
    "instanceType": "t2.nano",
    "licenseModel": "",
    "lookbackPeriodInDays": "7",
    "maximumNormalizedUnitsUsedPerHour": 7.81,
    "maximumNumberOfInstancesUsedPerHour": 96.4,
    "minimumNormalizedUnitsUsedPerHour": 8.31,
    "minimumNumberOfInstancesUsedPerHour": 93.37,
    "nodeType": "t2.nano",
    "paymentOption": "Partial_Upfront",
    "platform": "",
    "productDescription": "Linux/UNIX",
    "recommendedNormalizedUnitsToPurchase": "2",
    "recommendedNumberOfInstancesToPurchase": "2",
    "recurringStandardMonthlyCost": "3.66",
    "region": "EU (Paris)",
    "resourceType": "t2",
    "service": "Elastic Compute Cloud (EC2)",
    "sizeFlexEligible": "false",
    "tenancy": "Shared",
    "term": "1 year",
    "upfrontCost": "441.08"
  },
  {
    "accountID": "353197488767",
    "accountName": "fierceowl",
    "accountScope": "Linked",
    "availabilityZone": "",
    "averageNormalizedUnitsUsedPerHour": 653.69,
    "averageNumberOfInstancesUsedPerHour": 691.38,
    "averageUtilization": "31",
    "databaseEdition": "",
    "databaseEngine": "",
    "deploymentOption": "",
    "estimatedBreakEvenInMonths": "3.00",
    "estimatedMonthlyOnDemandCost": "7.63",
    "estimatedMonthlySavingsAmount": "270.53",
    "estimatedMonthlySavingsPercentage": "28",
    "estimatedReservationCostForLookbackPeriod": "7.84",
    "family": "r5",
    "instanceClass": "",
    "instanceSize": "",
    "instanceType": "r5.large",
    "licenseModel": "",
    "lookbackPeriodInDays": "7",
    "maximumNormalizedUnitsUsedPerHour": 8.33,
    "maximumNumberOfInstancesUsedPerHour": 39.34,
    "minimumNormalizedUnitsUsedPerHour": 73.56,
    "minimumNumberOfInstancesUsedPerHour": 50.5,
    "nodeType": "r5.large",
    "paymentOption": "Partial_Upfront",
    "platform": "",
    "productDescription": "Linux/UNIX",
    "recommendedNormalizedUnitsToPurchase": "7",
    "recommendedNumberOfInstancesToPurchase": "4",
    "recurringStandardMonthlyCost": "424.82",
    "region": "Asia Pacific (Sydney)",
    "resourceType": "r5",
    "service": "Elastic Compute Cloud (EC2)",
    "sizeFlexEligible": "false",
    "tenancy": "Shared",
    "term": "1 year",
    "upfrontCost": "344.55"
  },
  {
    "accountID": "516702013600",
    "accountName": "sillyzebra",
    "accountScope": "Linked",
    "availabilityZone": "",
    "averageNormalizedUnitsUsedPerHour": 76.98,
    "averageNumberOfInstancesUsedPerHour": 723.79,
    "averageUtilization": "25",
    "databaseEdition": "",
    "databaseEngine": "",
    "deploymentOption": "",
    "estimatedBreakEvenInMonths": "10.71",
    "estimatedMonthlyOnDemandCost": "510.45",
    "estimatedMonthlySavingsAmount": "320.17",
    "estimatedMonthlySavingsPercentage": "14",
    "estimatedReservationCostForLookbackPeriod": "23.92",
    "family": "c5a",
    "instanceClass": "",
    "instanceSize": "",
    "instanceType": "c5a.large",
    "licenseModel": "",
    "lookbackPeriodInDays": "7",
    "maximumNormalizedUnitsUsedPerHour": 59.01,
    "maximumNumberOfInstancesUsedPerHour": 13.56,
    "minimumNormalizedUnitsUsedPerHour": 6.83,
    "minimumNumberOfInstancesUsedPerHour": 35.99,
    "nodeType": "c5a.large",
    "paymentOption": "Partial_Upfront",
    "platform": "",
    "productDescription": "Linux/UNIX",
    "recommendedNormalizedUnitsToPurchase": "8",
    "recommendedNumberOfInstancesToPurchase": "2",
    "recurringStandardMonthlyCost": "316.32",
    "region": "Asia Pacific (Tokyo)",
    "resourceType": "c5a",
    "service": "Elastic Compute Cloud (EC2)",
    "sizeFlexEligible": "false",
    "tenancy": "Shared",
    "term": "1 year",
    "upfrontCost": "405.02"
  },
  {
    "accountID": "999773517191",
    "accountName": "obedienturchin",
    "accountScope": "Linked",
    "availabilityZone": "",
    "averageNormalizedUnitsUsedPerHour": 902.32,
    "averageNumberOfInstancesUsedPerHour": 808.62,
    "averageUtilization": "93",
    "databaseEdition": "",
    "databaseEngine": "",
    "deploymentOption": "",
    "estimatedBreakEvenInMonths": "1.92",
    "estimatedMonthlyOnDemandCost": "688.15",
    "estimatedMonthlySavingsAmount": "459.39",
    "estimatedMonthlySavingsPercentage": "62",
    "estimatedReservationCostForLookbackPeriod": "1.80",
    "family": "i4i",
    "instanceClass": "",
    "instanceSize": "",
    "instanceType": "i4i.large",
    "licenseModel": "",
    "lookbackPeriodInDays": "7",
    "maximumNormalizedUnitsUsedPerHour": 44.1,
    "maximumNumberOfInstancesUsedPerHour": 57.31,
    "minimumNormalizedUnitsUsedPerHour": 87.76,
    "minimumNumberOfInstancesUsedPerHour": 45.06,
    "nodeType": "i4i.large",
    "paymentOption": "Partial_Upfront",
    "platform": "",
    "productDescription": "Linux/UNIX",
    "recommendedNormalizedUnitsToPurchase": "6",
    "recommendedNumberOfInstancesToPurchase": "8",
    "recurringStandardMonthlyCost": "92.76",
    "region": "EU (Frankfurt)",
    "resourceType": "i4i",
    "service": "Elastic Compute Cloud (EC2)",
    "sizeFlexEligible": "false",
    "tenancy": "Shared",
    "term": "1 year",
    "upfrontCost": "507.34"
  },
  {
    "accountID": "665319725593",
    "accountName": "jollyurchin",
    "accountScope": "Linked",
    "availabilityZone": "",
    "averageNormalizedUnitsUsedPerHour": 310.12,
    "averageNumberOfInstancesUsedPerHour": 857.21,
    "averageUtilization": "38",
    "databaseEdition": "",
    "databaseEngine": "",
    "deploymentOption": "",
    "estimatedBreakEvenInMonths": "57.71",
    "estimatedMonthlyOnDemandCost": "241.79",
    "estimatedMonthlySavingsAmount": "307.66",
    "estimatedMonthlySavingsPercentage": "72",
    "estimatedReservationCostForLookbackPeriod": "6.63",
    "family": "r5",
    "instanceClass": "",
    "instanceSize": "",
    "instanceType": "r5.large",
    "licenseModel": "",
    "lookbackPeriodInDays": "7",
    "maximumNormalizedUnitsUsedPerHour": 77.41,
    "maximumNumberOfInstancesUsedPerHour": 77.77,
    "minimumNormalizedUnitsUsedPerHour": 4.68,
    "minimumNumberOfInstancesUsedPerHour": 63.7,
    "nodeType": "r5.large",
    "paymentOption": "Partial_Upfront",
    "platform": "",
    "productDescription": "Linux/UNIX",
    "recommendedNormalizedUnitsToPurchase": "9",
    "recommendedNumberOfInstancesToPurchase": "4",
    "recurringStandardMonthlyCost": "37.34",
    "region": "Asia Pacific (Mumbai)",
    "resourceType": "r5",
    "service": "Elastic Compute Cloud (EC2)",
    "sizeFlexEligible": "false",
    "tenancy": "Shared",
    "term": "1 year",
    "upfrontCost": "32.81"
  },
  {
    "accountID": "165283112664",
    "accountName": "calmhorse",
    "accountScope": "Linked",
    "availabilityZone": "",
    "averageNormalizedUnitsUsedPerHour": 42.3,
    "averageNumberOfInstancesUsedPerHour": 877.88,
    "averageUtilization": "95",
    "databaseEdition": "",
    "databaseEngine": "",
    "deploymentOption": "",
    "estimatedBreakEvenInMonths": "7.26",
    "estimatedMonthlyOnDemandCost": "13.73",
    "estimatedMonthlySavingsAmount": "123.44",
    "estimatedMonthlySavingsPercentage": "83",
    "estimatedReservationCostForLookbackPeriod": "2.61",
    "family": "g4dn",
    "instanceClass": "",
    "instanceSize": "",
    "instanceType": "g4dn.xlarge",
    "licenseModel": "",
    "lookbackPeriodInDays": "7",
    "maximumNormalizedUnitsUsedPerHour": 81.4,
    "maximumNumberOfInstancesUsedPerHour": 6.07,
    "minimumNormalizedUnitsUsedPerHour": 4.14,
    "minimumNumberOfInstancesUsedPerHour": 11.54,
    "nodeType": "g4dn.xlarge",
    "paymentOption": "Partial_Upfront",
    "platform": "",
    "productDescription": "Linux/UNIX",
    "recommendedNormalizedUnitsToPurchase": "5",
    "recommendedNumberOfInstancesToPurchase": "1",
    "recurringStandardMonthlyCost": "185.01",
    "region": "US East (N. Virginia)",
    "resourceType": "g4dn",
    "service": "Elastic Compute Cloud (EC2)",
    "sizeFlexEligible": "false",
    "tenancy": "Shared",
    "term": "1 year",
    "upfrontCost": "320.73"
  },
  {
    "accountID": "999773517191",
    "accountName": "fiercelion",
    "accountScope": "Linked",
    "availabilityZone": "",
    "averageNormalizedUnitsUsedPerHour": 544.01,
    "averageNumberOfInstancesUsedPerHour": 388.71,
    "averageUtilization": "14",
    "databaseEdition": "",
    "databaseEngine": "",
    "deploymentOption": "",
    "estimatedBreakEvenInMonths": "96.22",
    "estimatedMonthlyOnDemandCost": "51.27",
    "estimatedMonthlySavingsAmount": "10.97",
    "estimatedMonthlySavingsPercentage": "20",
    "estimatedReservationCostForLookbackPeriod": "33.06",
    "family": "t2",
    "instanceClass": "",
    "instanceSize": "",
    "instanceType": "t2.nano",
    "licenseModel": "",
    "lookbackPeriodInDays": "7",
    "maximumNormalizedUnitsUsedPerHour": 1.86,
    "maximumNumberOfInstancesUsedPerHour": 62.12,
    "minimumNormalizedUnitsUsedPerHour": 0.36,
    "minimumNumberOfInstancesUsedPerHour": 33.83,
    "nodeType": "t2.nano",
    "paymentOption": "Partial_Upfront",
    "platform": "",
    "productDescription": "Linux/UNIX",
    "recommendedNormalizedUnitsToPurchase": "0",
    "recommendedNumberOfInstancesToPurchase": "6",
    "recurringStandardMonthlyCost": "313.79",
    "region": "EU (Frankfurt)",
    "resourceType": "t2",
    "service": "Elastic Compute Cloud (EC2)",
    "sizeFlexEligible": "false",
    "tenancy": "Shared",
    "term": "1 year",
    "upfrontCost": "471.70"
  },
  {
    "accountID": "620368136857",
    "accountName": "jovialparrot",
    "accountScope": "Linked",
    "availabilityZone": "",
    "averageNormalizedUnitsUsedPerHour": 264.36,
    "averageNumberOfInstancesUsedPerHour": 423.15,
    "averageUtilization": "43",
    "databaseEdition": "",
    "databaseEngine": "",
    "deploymentOption": "",
    "estimatedBreakEvenInMonths": "1.13",
    "estimatedMonthlyOnDemandCost": "20.69",
    "estimatedMonthlySavingsAmount": "344.43",
    "estimatedMonthlySavingsPercentage": "43",
    "estimatedReservationCostForLookbackPeriod": "0.77",
    "family": "t2",
    "instanceClass": "",
    "instanceSize": "",
    "instanceType": "t2.nano",
    "licenseModel": "",
    "lookbackPeriodInDays": "7",
    "maximumNormalizedUnitsUsedPerHour": 26.21,
    "maximumNumberOfInstancesUsedPerHour": 22.43,
    "minimumNormalizedUnitsUsedPerHour": 61.49,
    "minimumNumberOfInstancesUsedPerHour": 72.46,
    "nodeType": "t2.nano",
    "paymentOption": "Partial_Upfront",
    "platform": "",
    "productDescription": "Linux/UNIX",
    "recommendedNormalizedUnitsToPurchase": "3",
    "recommendedNumberOfInstancesToPurchase": "3",
    "recurringStandardMonthlyCost": "35.51",
    "region": "Asia Pacific (Tokyo)",
    "resourceType": "t2",
    "service": "Elastic Compute Cloud (EC2)",
    "sizeFlexEligible": "false",
    "tenancy": "Shared",
    "term": "1 year",
    "upfrontCost": "301.04"
  },
  {
    "accountID": "646728909564",
    "accountName": "excitedgoat",
    "accountScope": "Linked",
    "availabilityZone": "",
    "averageNormalizedUnitsUsedPerHour": 938.53,
    "averageNumberOfInstancesUsedPerHour": 304.79,
    "averageUtilization": "42",
    "databaseEdition": "",
    "databaseEngine": "",
    "deploymentOption": "",
    "estimatedBreakEvenInMonths": "9.08",
    "estimatedMonthlyOnDemandCost": "125.36",
    "estimatedMonthlySavingsAmount": "579.21",
    "estimatedMonthlySavingsPercentage": "49",
    "estimatedReservationCostForLookbackPeriod": "26.12",
    "family": "t2",
    "instanceClass": "",
    "instanceSize": "",
    "instanceType": "t2.nano",
    "licenseModel": "",
    "lookbackPeriodInDays": "7",
    "maximumNormalizedUnitsUsedPerHour": 88.53,
    "maximumNumberOfInstancesUsedPerHour": 69.93,
    "minimumNormalizedUnitsUsedPerHour": 1.92,
    "minimumNumberOfInstancesUsedPerHour": 42.93,
    "nodeType": "t2.nano",
    "paymentOption": "Partial_Upfront",
    "platform": "",
    "productDescription": "Linux/UNIX",
    "recommendedNormalizedUnitsToPurchase": "6",
    "recommendedNumberOfInstancesToPurchase": "8",
    "recurringStandardMonthlyCost": "368.61",
    "region": "US East (N. Virginia)",
    "resourceType": "t2",
    "service": "Elastic Compute Cloud (EC2)",
    "sizeFlexEligible": "false",
    "tenancy": "Shared",
    "term": "1 year",
    "upfrontCost": "42.10"
  },
  {
    "accountID": "165283112664",
    "accountName": "eagerowl",
    "accountScope": "Linked",
    "availabilityZone": "",
    "averageNormalizedUnitsUsedPerHour": 594.02,
    "averageNumberOfInstancesUsedPerHour": 482.27,
    "averageUtilization": "69",
    "databaseEdition": "",
    "databaseEngine": "",
    "deploymentOption": "",
    "estimatedBreakEvenInMonths": "29.81",
    "estimatedMonthlyOnDemandCost": "147.13",
    "estimatedMonthlySavingsAmount": "427.16",
    "estimatedMonthlySavingsPercentage": "79",
    "estimatedReservationCostForLookbackPeriod": "12.50",
    "family": "c4",
    "instanceClass": "",
    "instanceSize": "",
    "instanceType": "c4.large",
    "licenseModel": "",
    "lookbackPeriodInDays": "7",
    "maximumNormalizedUnitsUsedPerHour": 22.13,
    "maximumNumberOfInstancesUsedPerHour": 59.34,
    "minimumNormalizedUnitsUsedPerHour": 68.36,
    "minimumNumberOfInstancesUsedPerHour": 23.4,
    "nodeType": "c4.large",
    "paymentOption": "Partial_Upfront",
    "platform": "",
    "productDescription": "Linux/UNIX",
    "recommendedNormalizedUnitsToPurchase": "9",
    "recommendedNumberOfInstancesToPurchase": "4",
    "recurringStandardMonthlyCost": "531.28",
    "region": "US East (N. Virginia)",
    "resourceType": "c4",
    "service": "Elastic Compute Cloud (EC2)",
    "sizeFlexEligible": "false",
    "tenancy": "Shared",
    "term": "1 year",
    "upfrontCost": "66.90"
  },
  {
    "accountID": "627286410625",
    "accountName": "obedientfox",
    "accountScope": "Linked",
    "availabilityZone": "",
    "averageNormalizedUnitsUsedPerHour": 809.93,
    "averageNumberOfInstancesUsedPerHour": 204.45,
    "averageUtilization": "54",
    "databaseEdition": "",
    "databaseEngine": "",
    "deploymentOption": "",
    "estimatedBreakEvenInMonths": "17.99",
    "estimatedMonthlyOnDemandCost": "633.08",
    "estimatedMonthlySavingsAmount": "236.77",
    "estimatedMonthlySavingsPercentage": "59",
    "estimatedReservationCostForLookbackPeriod": "38.44",
    "family": "c4",
    "instanceClass": "",
    "instanceSize": "",
    "instanceType": "c4.large",
    "licenseModel": "",
    "lookbackPeriodInDays": "7",
    "maximumNormalizedUnitsUsedPerHour": 42.06,
    "maximumNumberOfInstancesUsedPerHour": 33.91,
    "minimumNormalizedUnitsUsedPerHour": 13.59,
    "minimumNumberOfInstancesUsedPerHour": 34.78,
    "nodeType": "c4.large",
    "paymentOption": "Partial_Upfront",
    "platform": "",
    "productDescription": "Linux/UNIX",
    "recommendedNormalizedUnitsToPurchase": "9",
    "recommendedNumberOfInstancesToPurchase": "4",
    "recurringStandardMonthlyCost": "385.80",
    "region": "US West (Oregon)",
    "resourceType": "c4",
    "service": "Elastic Compute Cloud (EC2)",
    "sizeFlexEligible": "false",
    "tenancy": "Shared",
    "term": "1 year",
    "upfrontCost": "409.66"
  },
  {
    "accountID": "999773517191",
    "accountName": "drowsypenguin",
    "accountScope": "Linked",
    "availabilityZone": "",
    "averageNormalizedUnitsUsedPerHour": 220.97,
    "averageNumberOfInstancesUsedPerHour": 59.59,
    "averageUtilization": "22",
    "databaseEdition": "",
    "databaseEngine": "",
    "deploymentOption": "",
    "estimatedBreakEvenInMonths": "3.34",
    "estimatedMonthlyOnDemandCost": "250.85",
    "estimatedMonthlySavingsAmount": "279.93",
    "estimatedMonthlySavingsPercentage": "34",
    "estimatedReservationCostForLookbackPeriod": "14.26",
    "family": "r5",
    "instanceClass": "",
    "instanceSize": "",
    "instanceType": "r5.large",
    "licenseModel": "",
    "lookbackPeriodInDays": "7",
    "maximumNormalizedUnitsUsedPerHour": 12.88,
    "maximumNumberOfInstancesUsedPerHour": 32.22,
    "minimumNormalizedUnitsUsedPerHour": 72.32,
    "minimumNumberOfInstancesUsedPerHour": 10.12,
    "nodeType": "r5.large",
    "paymentOption": "Partial_Upfront",
    "platform": "",
    "productDescription": "Linux/UNIX",
    "recommendedNormalizedUnitsToPurchase": "7",
    "recommendedNumberOfInstancesToPurchase": "9",
    "recurringStandardMonthlyCost": "28.90",
    "region": "EU (Paris)",
    "resourceType": "r5",
    "service": "Elastic Compute Cloud (EC2)",
    "sizeFlexEligible": "false",
    "tenancy": "Shared",
    "term": "1 year",
    "upfrontCost": "287.40"
  },
  {
    "accountID": "620368136857",
    "accountName": "youthfulyak",
    "accountScope": "Linked",
    "availabilityZone": "",
    "averageNormalizedUnitsUsedPerHour": 132.47,
    "averageNumberOfInstancesUsedPerHour": 250.03,
    "averageUtilization": "62",
    "databaseEdition": "",
    "databaseEngine": "",
    "deploymentOption": "",
    "estimatedBreakEvenInMonths": "28.26",
    "estimatedMonthlyOnDemandCost": "138.87",
    "estimatedMonthlySavingsAmount": "455.57",
    "estimatedMonthlySavingsPercentage": "52",
    "estimatedReservationCostForLookbackPeriod": "59.51",
    "family": "m5",
    "instanceClass": "",
    "instanceSize": "",
    "instanceType": "m5.large",
    "licenseModel": "",
    "lookbackPeriodInDays": "7",
    "maximumNormalizedUnitsUsedPerHour": 80.06,
    "maximumNumberOfInstancesUsedPerHour": 68.12,
    "minimumNormalizedUnitsUsedPerHour": 34.03,
    "minimumNumberOfInstancesUsedPerHour": 65.82,
    "nodeType": "m5.large",
    "paymentOption": "Partial_Upfront",
    "platform": "",
    "productDescription": "Linux/UNIX",
    "recommendedNormalizedUnitsToPurchase": "6",
    "recommendedNumberOfInstancesToPurchase": "7",
    "recurringStandardMonthlyCost": "284.49",
    "region": "Asia Pacific (Sydney)",
    "resourceType": "m5",
    "service": "Elastic Compute Cloud (EC2)",
    "sizeFlexEligible": "false",
    "tenancy": "Shared",
    "term": "1 year",
    "upfrontCost": "275.85"
  },
  {
    "accountID": "516702013600",
    "accountName": "happyfox",
    "accountScope": "Linked",
    "availabilityZone": "",
    "averageNormalizedUnitsUsedPerHour": 808.74,
    "averageNumberOfInstancesUsedPerHour": 506.45,
    "averageUtilization": "23",
    "databaseEdition": "",
    "databaseEngine": "",
    "deploymentOption": "",
    "estimatedBreakEvenInMonths": "12.31",
    "estimatedMonthlyOnDemandCost": "348.73",
    "estimatedMonthlySavingsAmount": "726.03",
    "estimatedMonthlySavingsPercentage": "38",
    "estimatedReservationCostForLookbackPeriod": "79.14",
    "family": "g4dn",
    "instanceClass": "",
    "instanceSize": "",
    "instanceType": "g4dn.xlarge",
    "licenseModel": "",
    "lookbackPeriodInDays": "7",
    "maximumNormalizedUnitsUsedPerHour": 51.34,
    "maximumNumberOfInstancesUsedPerHour": 4.63,
    "minimumNormalizedUnitsUsedPerHour": 11.42,
    "minimumNumberOfInstancesUsedPerHour": 12.93,
    "nodeType": "g4dn.xlarge",
    "paymentOption": "Partial_Upfront",
    "platform": "",
    "productDescription": "Linux/UNIX",
    "recommendedNormalizedUnitsToPurchase": "8",
    "recommendedNumberOfInstancesToPurchase": "2",
    "recurringStandardMonthlyCost": "313.58",
    "region": "Asia Pacific (Tokyo)",
    "resourceType": "g4dn",
    "service": "Elastic Compute Cloud (EC2)",
    "sizeFlexEligible": "false",
    "tenancy": "Shared",
    "term": "1 year",
    "upfrontCost": "390.95"
  },
  {
    "accountID": "646728909564",
    "accountName": "eagercat",
    "accountScope": "Linked",
    "availabilityZone": "",
    "averageNormalizedUnitsUsedPerHour": 774.31,
    "averageNumberOfInstancesUsedPerHour": 397.09,
    "averageUtilization": "93",
    "databaseEdition": "",
    "databaseEngine": "",
    "deploymentOption": "",
    "estimatedBreakEvenInMonths": "56.37",
    "estimatedMonthlyOnDemandCost": "709.32",
    "estimatedMonthlySavingsAmount": "0.41",
    "estimatedMonthlySavingsPercentage": "48",
    "estimatedReservationCostForLookbackPeriod": "42.77",
    "family": "t2",
    "instanceClass": "",
    "instanceSize": "",
    "instanceType": "t2.nano",
    "licenseModel": "",
    "lookbackPeriodInDays": "7",
    "maximumNormalizedUnitsUsedPerHour": 64.46,
    "maximumNumberOfInstancesUsedPerHour": 32.9,
    "minimumNormalizedUnitsUsedPerHour": 60.52,
    "minimumNumberOfInstancesUsedPerHour": 94.66,
    "nodeType": "t2.nano",
    "paymentOption": "Partial_Upfront",
    "platform": "",
    "productDescription": "Linux/UNIX",
    "recommendedNormalizedUnitsToPurchase": "0",
    "recommendedNumberOfInstancesToPurchase": "1",
    "recurringStandardMonthlyCost": "8.35",
    "region": "Asia Pacific (Singapore)",
    "resourceType": "t2",
    "service": "Elastic Compute Cloud (EC2)",
    "sizeFlexEligible": "false",
    "tenancy": "Shared",
    "term": "1 year",
    "upfrontCost": "674.50"
  },
  {
    "accountID": "138186646095",
    "accountName": "happypenguin",
    "accountScope": "Linked",
    "availabilityZone": "",
    "averageNormalizedUnitsUsedPerHour": 100.85,
    "averageNumberOfInstancesUsedPerHour": 949.7,
    "averageUtilization": "85",
    "databaseEdition": "",
    "databaseEngine": "",
    "deploymentOption": "",
    "estimatedBreakEvenInMonths": "7.62",
    "estimatedMonthlyOnDemandCost": "155.96",
    "estimatedMonthlySavingsAmount": "230.43",
    "estimatedMonthlySavingsPercentage": "92",
    "estimatedReservationCostForLookbackPeriod": "15.70",
    "family": "c4",
    "instanceClass": "",
    "instanceSize": "",
    "instanceType": "c4.large",
    "licenseModel": "",
    "lookbackPeriodInDays": "7",
    "maximumNormalizedUnitsUsedPerHour": 63.01,
    "maximumNumberOfInstancesUsedPerHour": 15.49,
    "minimumNormalizedUnitsUsedPerHour": 59.98,
    "minimumNumberOfInstancesUsedPerHour": 38.62,
    "nodeType": "c4.large",
    "paymentOption": "Partial_Upfront",
    "platform": "",
    "productDescription": "Linux/UNIX",
    "recommendedNormalizedUnitsToPurchase": "4",
    "recommendedNumberOfInstancesToPurchase": "2",
    "recurringStandardMonthlyCost": "73.21",
    "region": "EU (Frankfurt)",
    "resourceType": "c4",
    "service": "Elastic Compute Cloud (EC2)",
    "sizeFlexEligible": "false",
    "tenancy": "Shared",
    "term": "1 year",
    "upfrontCost": "6.02"
  },
  {
    "accountID": "627286410625",
    "accountName": "thankfulnewt",
    "accountScope": "Linked",
    "availabilityZone": "",
    "averageNormalizedUnitsUsedPerHour": 507.26,
    "averageNumberOfInstancesUsedPerHour": 827.48,
    "averageUtilization": "92",
    "databaseEdition": "",
    "databaseEngine": "",
    "deploymentOption": "",
    "estimatedBreakEvenInMonths": "47.09",
    "estimatedMonthlyOnDemandCost": "58.90",
    "estimatedMonthlySavingsAmount": "216.47",
    "estimatedMonthlySavingsPercentage": "19",
    "estimatedReservationCostForLookbackPeriod": "14.01",
    "family": "t2",
    "instanceClass": "",
    "instanceSize": "",
    "instanceType": "t2.nano",
    "licenseModel": "",
    "lookbackPeriodInDays": "7",
    "maximumNormalizedUnitsUsedPerHour": 62.9,
    "maximumNumberOfInstancesUsedPerHour": 77.29,
    "minimumNormalizedUnitsUsedPerHour": 18.68,
    "minimumNumberOfInstancesUsedPerHour": 21.04,
    "nodeType": "t2.nano",
    "paymentOption": "Partial_Upfront",
    "platform": "",
    "productDescription": "Linux/UNIX",
    "recommendedNormalizedUnitsToPurchase": "2",
    "recommendedNumberOfInstancesToPurchase": "7",
    "recurringStandardMonthlyCost": "645.62",
    "region": "EU (Paris)",
    "resourceType": "t2",
    "service": "Elastic Compute Cloud (EC2)",
    "sizeFlexEligible": "false",
    "tenancy": "Shared",
    "term": "1 year",
    "upfrontCost": "549.81"
  },
  {
    "accountID": "165283112664",
    "accountName": "happyviper",
    "accountScope": "Linked",
    "availabilityZone": "",
    "averageNormalizedUnitsUsedPerHour": 342.06,
    "averageNumberOfInstancesUsedPerHour": 965.4,
    "averageUtilization": "30",
    "databaseEdition": "",
    "databaseEngine": "",
    "deploymentOption": "",
    "estimatedBreakEvenInMonths": "41.96",
    "estimatedMonthlyOnDemandCost": "366.75",
    "estimatedMonthlySavingsAmount": "39.64",
    "estimatedMonthlySavingsPercentage": "16",
    "estimatedReservationCostForLookbackPeriod": "79.36",
    "family": "m5",
    "instanceClass": "",
    "instanceSize": "",
    "instanceType": "m5.large",
    "licenseModel": "",
    "lookbackPeriodInDays": "7",
    "maximumNormalizedUnitsUsedPerHour": 37.95,
    "maximumNumberOfInstancesUsedPerHour": 84.21,
    "minimumNormalizedUnitsUsedPerHour": 46.07,
    "minimumNumberOfInstancesUsedPerHour": 78.71,
    "nodeType": "m5.large",
    "paymentOption": "Partial_Upfront",
    "platform": "",
    "productDescription": "Linux/UNIX",
    "recommendedNormalizedUnitsToPurchase": "7",
    "recommendedNumberOfInstancesToPurchase": "3",
    "recurringStandardMonthlyCost": "29.90",
    "region": "US East (N. Virginia)",
    "resourceType": "m5",
    "service": "Elastic Compute Cloud (EC2)",
    "sizeFlexEligible": "false",
    "tenancy": "Shared",
    "term": "1 year",
    "upfrontCost": "178.51"
  },
  {
    "accountID": "646728909564",
    "accountName": "zealousnewt",
    "accountScope": "Linked",
    "availabilityZone": "",
    "averageNormalizedUnitsUsedPerHour": 681.09,
    "averageNumberOfInstancesUsedPerHour": 750.55,
    "averageUtilization": "44",
    "databaseEdition": "",
    "databaseEngine": "",
    "deploymentOption": "",
    "estimatedBreakEvenInMonths": "30.69",
    "estimatedMonthlyOnDemandCost": "782.67",
    "estimatedMonthlySavingsAmount": "43.00",
    "estimatedMonthlySavingsPercentage": "16",
    "estimatedReservationCostForLookbackPeriod": "26.56",
    "family": "t3",
    "instanceClass": "",
    "instanceSize": "",
    "instanceType": "t3.nano",
    "licenseModel": "",
    "lookbackPeriodInDays": "7",
    "maximumNormalizedUnitsUsedPerHour": 35.99,
    "maximumNumberOfInstancesUsedPerHour": 63.11,
    "minimumNormalizedUnitsUsedPerHour": 50.91,
    "minimumNumberOfInstancesUsedPerHour": 94.71,
    "nodeType": "t3.nano",
    "paymentOption": "Partial_Upfront",
    "platform": "",
    "productDescription": "Linux/UNIX",
    "recommendedNormalizedUnitsToPurchase": "6",
    "recommendedNumberOfInstancesToPurchase": "2",
    "recurringStandardMonthlyCost": "813.01",
    "region": "EU (Frankfurt)",
    "resourceType": "t3",
    "service": "Elastic Compute Cloud (EC2)",
    "sizeFlexEligible": "false",
    "tenancy": "Shared",
    "term": "1 year",
    "upfrontCost": "866.98"
  },
  {
    "accountID": "138186646095",
    "accountName": "proudnewt",
    "accountScope": "Linked",
    "availabilityZone": "",
    "averageNormalizedUnitsUsedPerHour": 864.24,
    "averageNumberOfInstancesUsedPerHour": 655.78,
    "averageUtilization": "94",
    "databaseEdition": "",
    "databaseEngine": "",
    "deploymentOption": "",
    "estimatedBreakEvenInMonths": "6.07",
    "estimatedMonthlyOnDemandCost": "247.05",
    "estimatedMonthlySavingsAmount": "49.79",
    "estimatedMonthlySavingsPercentage": "38",
    "estimatedReservationCostForLookbackPeriod": "6.40",
    "family": "c5",
    "instanceClass": "",
    "instanceSize": "",
    "instanceType": "c5.xlarge",
    "licenseModel": "",
    "lookbackPeriodInDays": "7",
    "maximumNormalizedUnitsUsedPerHour": 99.36,
    "maximumNumberOfInstancesUsedPerHour": 25.37,
    "minimumNormalizedUnitsUsedPerHour": 85.48,
    "minimumNumberOfInstancesUsedPerHour": 95.39,
    "nodeType": "c5.xlarge",
    "paymentOption": "Partial_Upfront",
    "platform": "",
    "productDescription": "Linux/UNIX",
    "recommendedNormalizedUnitsToPurchase": "7",
    "recommendedNumberOfInstancesToPurchase": "7",
    "recurringStandardMonthlyCost": "482.46",
    "region": "EU (Frankfurt)",
    "resourceType": "c5",
    "service": "Elastic Compute Cloud (EC2)",
    "sizeFlexEligible": "false",
    "tenancy": "Shared",
    "term": "1 year",
    "upfrontCost": "273.90"
  },
  {
    "accountID": "665319725593",
    "accountName": "happygoat",
    "accountScope": "Linked",
    "availabilityZone": "",
    "averageNormalizedUnitsUsedPerHour": 752.55,
    "averageNumberOfInstancesUsedPerHour": 454.36,
    "averageUtilization": "88",
    "databaseEdition": "",
    "databaseEngine": "",
    "deploymentOption": "",
    "estimatedBreakEvenInMonths": "1.82",
    "estimatedMonthlyOnDemandCost": "195.44",
    "estimatedMonthlySavingsAmount": "318.23",
    "estimatedMonthlySavingsPercentage": "50",
    "estimatedReservationCostForLookbackPeriod": "69.94",
    "family": "c5",
    "instanceClass": "",
    "instanceSize": "",
    "instanceType": "c5.xlarge",
    "licenseModel": "",
    "lookbackPeriodInDays": "7",
    "maximumNormalizedUnitsUsedPerHour": 3.28,
    "maximumNumberOfInstancesUsedPerHour": 31.93,
    "minimumNormalizedUnitsUsedPerHour": 76.6,
    "minimumNumberOfInstancesUsedPerHour": 61.18,
    "nodeType": "c5.xlarge",
    "paymentOption": "Partial_Upfront",
    "platform": "",
    "productDescription": "Linux/UNIX",
    "recommendedNormalizedUnitsToPurchase": "5",
    "recommendedNumberOfInstancesToPurchase": "3",
    "recurringStandardMonthlyCost": "757.09",
    "region": "Asia Pacific (Mumbai)",
    "resourceType": "c5",
    "service": "Elastic Compute Cloud (EC2)",
    "sizeFlexEligible": "false",
    "tenancy": "Shared",
    "term": "1 year",
    "upfrontCost": "204.91"
  },
  {
    "accountID": "516702013600",
    "accountName": "wittysnake",
    "accountScope": "Linked",
    "availabilityZone": "",
    "averageNormalizedUnitsUsedPerHour": 703.6,
    "averageNumberOfInstancesUsedPerHour": 743.14,
    "averageUtilization": "49",
    "databaseEdition": "",
    "databaseEngine": "",
    "deploymentOption": "",
    "estimatedBreakEvenInMonths": "34.12",
    "estimatedMonthlyOnDemandCost": "32.85",
    "estimatedMonthlySavingsAmount": "283.70",
    "estimatedMonthlySavingsPercentage": "45",
    "estimatedReservationCostForLookbackPeriod": "16.62",
    "family": "m5",
    "instanceClass": "",
    "instanceSize": "",
    "instanceType": "m5.large",
    "licenseModel": "",
    "lookbackPeriodInDays": "7",
    "maximumNormalizedUnitsUsedPerHour": 62.33,
    "maximumNumberOfInstancesUsedPerHour": 26.59,
    "minimumNormalizedUnitsUsedPerHour": 73.32,
    "minimumNumberOfInstancesUsedPerHour": 29.79,
    "nodeType": "m5.large",
    "paymentOption": "Partial_Upfront",
    "platform": "",
    "productDescription": "Linux/UNIX",
    "recommendedNormalizedUnitsToPurchase": "2",
    "recommendedNumberOfInstancesToPurchase": "9",
    "recurringStandardMonthlyCost": "225.39",
    "region": "EU (London)",
    "resourceType": "m5",
    "service": "Elastic Compute Cloud (EC2)",
    "sizeFlexEligible": "false",
    "tenancy": "Shared",
    "term": "1 year",
    "upfrontCost": "678.75"
  },
  {
    "accountID": "646728909564",
    "accountName": "relievedcat",
    "accountScope": "Linked",
    "availabilityZone": "",
    "averageNormalizedUnitsUsedPerHour": 883.17,
    "averageNumberOfInstancesUsedPerHour": 338.22,
    "averageUtilization": "54",
    "databaseEdition": "",
    "databaseEngine": "",
    "deploymentOption": "",
    "estimatedBreakEvenInMonths": "28.63",
    "estimatedMonthlyOnDemandCost": "741.67",
    "estimatedMonthlySavingsAmount": "928.89",
    "estimatedMonthlySavingsPercentage": "38",
    "estimatedReservationCostForLookbackPeriod": "52.22",
    "family": "m5",
    "instanceClass": "",
    "instanceSize": "",
    "instanceType": "m5.large",
    "licenseModel": "",
    "lookbackPeriodInDays": "7",
    "maximumNormalizedUnitsUsedPerHour": 43.39,
    "maximumNumberOfInstancesUsedPerHour": 1.41,
    "minimumNormalizedUnitsUsedPerHour": 13.59,
    "minimumNumberOfInstancesUsedPerHour": 33.52,
    "nodeType": "m5.large",
    "paymentOption": "Partial_Upfront",
    "platform": "",
    "productDescription": "Linux/UNIX",
    "recommendedNormalizedUnitsToPurchase": "2",
    "recommendedNumberOfInstancesToPurchase": "9",
    "recurringStandardMonthlyCost": "4.07",
    "region": "US East (N. Virginia)",
    "resourceType": "m5",
    "service": "Elastic Compute Cloud (EC2)",
    "sizeFlexEligible": "false",
    "tenancy": "Shared",
    "term": "1 year",
    "upfrontCost": "480.31"
  },
  {
    "accountID": "620368136857",
    "accountName": "sillywhale",
    "accountScope": "Linked",
    "availabilityZone": "",
    "averageNormalizedUnitsUsedPerHour": 474.06,
    "averageNumberOfInstancesUsedPerHour": 811.17,
    "averageUtilization": "85",
    "databaseEdition": "",
    "databaseEngine": "",
    "deploymentOption": "",
    "estimatedBreakEvenInMonths": "7.96",
    "estimatedMonthlyOnDemandCost": "186.61",
    "estimatedMonthlySavingsAmount": "121.66",
    "estimatedMonthlySavingsPercentage": "52",
    "estimatedReservationCostForLookbackPeriod": "14.56",
    "family": "c5",
    "instanceClass": "",
    "instanceSize": "",
    "instanceType": "c5.xlarge",
    "licenseModel": "",
    "lookbackPeriodInDays": "7",
    "maximumNormalizedUnitsUsedPerHour": 0.27,
    "maximumNumberOfInstancesUsedPerHour": 40.84,
    "minimumNormalizedUnitsUsedPerHour": 81.57,
    "minimumNumberOfInstancesUsedPerHour": 74.55,
    "nodeType": "c5.xlarge",
    "paymentOption": "Partial_Upfront",
    "platform": "",
    "productDescription": "Linux/UNIX",
    "recommendedNormalizedUnitsToPurchase": "1",
    "recommendedNumberOfInstancesToPurchase": "6",
    "recurringStandardMonthlyCost": "55.54",
    "region": "Asia Pacific (Tokyo)",
    "resourceType": "c5",
    "service": "Elastic Compute Cloud (EC2)",
    "sizeFlexEligible": "false",
    "tenancy": "Shared",
    "term": "1 year",
    "upfrontCost": "2.22"
  },
  {
    "accountID": "165283112664",
    "accountName": "thankfulcat",
    "accountScope": "Linked",
    "availabilityZone": "",
    "averageNormalizedUnitsUsedPerHour": 331.62,
    "averageNumberOfInstancesUsedPerHour": 550.61,
    "averageUtilization": "43",
    "databaseEdition": "",
    "databaseEngine": "",
    "deploymentOption": "",
    "estimatedBreakEvenInMonths": "75.45",
    "estimatedMonthlyOnDemandCost": "483.71",
    "estimatedMonthlySavingsAmount": "288.97",
    "estimatedMonthlySavingsPercentage": "20",
    "estimatedReservationCostForLookbackPeriod": "18.07",
    "family": "c5",
    "instanceClass": "",
    "instanceSize": "",
    "instanceType": "c5.xlarge",
    "licenseModel": "",
    "lookbackPeriodInDays": "7",
    "maximumNormalizedUnitsUsedPerHour": 89.63,
    "maximumNumberOfInstancesUsedPerHour": 6.84,
    "minimumNormalizedUnitsUsedPerHour": 90.64,
    "minimumNumberOfInstancesUsedPerHour": 15.04,
    "nodeType": "c5.xlarge",
    "paymentOption": "Partial_Upfront",
    "platform": "",
    "productDescription": "Linux/UNIX",
    "recommendedNormalizedUnitsToPurchase": "4",
    "recommendedNumberOfInstancesToPurchase": "6",
    "recurringStandardMonthlyCost": "333.83",
    "region": "EU (Paris)",
    "resourceType": "c5",
    "service": "Elastic Compute Cloud (EC2)",
    "sizeFlexEligible": "false",
    "tenancy": "Shared",
    "term": "1 year",
    "upfrontCost": "5.64"
  },
  {
    "accountID": "627286410625",
    "accountName": "proudhorse",
    "accountScope": "Linked",
    "availabilityZone": "",
    "averageNormalizedUnitsUsedPerHour": 755.6,
    "averageNumberOfInstancesUsedPerHour": 957.71,
    "averageUtilization": "31",
    "databaseEdition": "",
    "databaseEngine": "",
    "deploymentOption": "",
    "estimatedBreakEvenInMonths": "14.52",
    "estimatedMonthlyOnDemandCost": "297.79",
    "estimatedMonthlySavingsAmount": "230.25",
    "estimatedMonthlySavingsPercentage": "31",
    "estimatedReservationCostForLookbackPeriod": "35.00",
    "family": "g4dn",
    "instanceClass": "",
    "instanceSize": "",
    "instanceType": "g4dn.xlarge",
    "licenseModel": "",
    "lookbackPeriodInDays": "7",
    "maximumNormalizedUnitsUsedPerHour": 37.35,
    "maximumNumberOfInstancesUsedPerHour": 66.17,
    "minimumNormalizedUnitsUsedPerHour": 33.87,
    "minimumNumberOfInstancesUsedPerHour": 97.83,
    "nodeType": "g4dn.xlarge",
    "paymentOption": "Partial_Upfront",
    "platform": "",
    "productDescription": "Linux/UNIX",
    "recommendedNormalizedUnitsToPurchase": "1",
    "recommendedNumberOfInstancesToPurchase": "7",
    "recurringStandardMonthlyCost": "103.19",
    "region": "EU (Ireland)",
    "resourceType": "g4dn",
    "service": "Elastic Compute Cloud (EC2)",
    "sizeFlexEligible": "false",
    "tenancy": "Shared",
    "term": "1 year",
    "upfrontCost": "177.63"
  },
  {
    "accountID": "646728909564",
    "accountName": "adventurousviper",
    "accountScope": "Linked",
    "availabilityZone": "",
    "averageNormalizedUnitsUsedPerHour": 79.64,
    "averageNumberOfInstancesUsedPerHour": 990.21,
    "averageUtilization": "71",
    "databaseEdition": "",
    "databaseEngine": "",
    "deploymentOption": "",
    "estimatedBreakEvenInMonths": "32.04",
    "estimatedMonthlyOnDemandCost": "454.08",
    "estimatedMonthlySavingsAmount": "10.06",
    "estimatedMonthlySavingsPercentage": "59",
    "estimatedReservationCostForLookbackPeriod": "65.03",
    "family": "m5",
    "instanceClass": "",
    "instanceSize": "",
    "instanceType": "m5.large",
    "licenseModel": "",
    "lookbackPeriodInDays": "7",
    "maximumNormalizedUnitsUsedPerHour": 81.29,
    "maximumNumberOfInstancesUsedPerHour": 87,
    "minimumNormalizedUnitsUsedPerHour": 18.47,
    "minimumNumberOfInstancesUsedPerHour": 42.28,
    "nodeType": "m5.large",
    "paymentOption": "Partial_Upfront",
    "platform": "",
    "productDescription": "Linux/UNIX",
    "recommendedNormalizedUnitsToPurchase": "2",
    "recommendedNumberOfInstancesToPurchase": "2",
    "recurringStandardMonthlyCost": "420.80",
    "region": "Asia Pacific (Singapore)",
    "resourceType": "m5",
    "service": "Elastic Compute Cloud (EC2)",
    "sizeFlexEligible": "false",
    "tenancy": "Shared",
    "term": "1 year",
    "upfrontCost": "64.52"
  },
  {
    "accountID": "627286410625",
    "accountName": "lazyant",
    "accountScope": "Linked",
    "availabilityZone": "",
    "averageNormalizedUnitsUsedPerHour": 827.53,
    "averageNumberOfInstancesUsedPerHour": 685.05,
    "averageUtilization": "33",
    "databaseEdition": "",
    "databaseEngine": "",
    "deploymentOption": "",
    "estimatedBreakEvenInMonths": "48.95",
    "estimatedMonthlyOnDemandCost": "0.12",
    "estimatedMonthlySavingsAmount": "299.35",
    "estimatedMonthlySavingsPercentage": "72",
    "estimatedReservationCostForLookbackPeriod": "22.00",
    "family": "t3",
    "instanceClass": "",
    "instanceSize": "",
    "instanceType": "t3.nano",
    "licenseModel": "",
    "lookbackPeriodInDays": "7",
    "maximumNormalizedUnitsUsedPerHour": 18.11,
    "maximumNumberOfInstancesUsedPerHour": 92.67,
    "minimumNormalizedUnitsUsedPerHour": 82.58,
    "minimumNumberOfInstancesUsedPerHour": 94.57,
    "nodeType": "t3.nano",
    "paymentOption": "Partial_Upfront",
    "platform": "",
    "productDescription": "Linux/UNIX",
    "recommendedNormalizedUnitsToPurchase": "3",
    "recommendedNumberOfInstancesToPurchase": "2",
    "recurringStandardMonthlyCost": "117.78",
    "region": "US West (Oregon)",
    "resourceType": "t3",
    "service": "Elastic Compute Cloud (EC2)",
    "sizeFlexEligible": "false",
    "tenancy": "Shared",
    "term": "1 year",
    "upfrontCost": "315.55"
  },
  {
    "accountID": "646728909564",
    "accountName": "kindhorse",
    "accountScope": "Linked",
    "availabilityZone": "",
    "averageNormalizedUnitsUsedPerHour": 604.69,
    "averageNumberOfInstancesUsedPerHour": 219.23,
    "averageUtilization": "83",
    "databaseEdition": "",
    "databaseEngine": "",
    "deploymentOption": "",
    "estimatedBreakEvenInMonths": "9.14",
    "estimatedMonthlyOnDemandCost": "10.39",
    "estimatedMonthlySavingsAmount": "223.87",
    "estimatedMonthlySavingsPercentage": "21",
    "estimatedReservationCostForLookbackPeriod": "4.78",
    "family": "t2",
    "instanceClass": "",
    "instanceSize": "",
    "instanceType": "t2.nano",
    "licenseModel": "",
    "lookbackPeriodInDays": "7",
    "maximumNormalizedUnitsUsedPerHour": 46.16,
    "maximumNumberOfInstancesUsedPerHour": 36.3,
    "minimumNormalizedUnitsUsedPerHour": 88.5,
    "minimumNumberOfInstancesUsedPerHour": 17.43,
    "nodeType": "t2.nano",
    "paymentOption": "Partial_Upfront",
    "platform": "",
    "productDescription": "Linux/UNIX",
    "recommendedNormalizedUnitsToPurchase": "6",
    "recommendedNumberOfInstancesToPurchase": "8",
    "recurringStandardMonthlyCost": "61.60",
    "region": "Asia Pacific (Tokyo)",
    "resourceType": "t2",
    "service": "Elastic Compute Cloud (EC2)",
    "sizeFlexEligible": "false",
    "tenancy": "Shared",
    "term": "1 year",
    "upfrontCost": "85.55"
  },
  {
    "accountID": "999773517191",
    "accountName": "gentleowl",
    "accountScope": "Linked",
    "availabilityZone": "",
    "averageNormalizedUnitsUsedPerHour": 913.12,
    "averageNumberOfInstancesUsedPerHour": 829.48,
    "averageUtilization": "75",
    "databaseEdition": "",
    "databaseEngine": "",
    "deploymentOption": "",
    "estimatedBreakEvenInMonths": "42.69",
    "estimatedMonthlyOnDemandCost": "126.93",
    "estimatedMonthlySavingsAmount": "416.12",
    "estimatedMonthlySavingsPercentage": "86",
    "estimatedReservationCostForLookbackPeriod": "24.03",
    "family": "c6i",
    "instanceClass": "",
    "instanceSize": "",
    "instanceType": "c6i.large",
    "licenseModel": "",
    "lookbackPeriodInDays": "7",
    "maximumNormalizedUnitsUsedPerHour": 75.54,
    "maximumNumberOfInstancesUsedPerHour": 24.18,
    "minimumNormalizedUnitsUsedPerHour": 35.31,
    "minimumNumberOfInstancesUsedPerHour": 87.7,
    "nodeType": "c6i.large",
    "paymentOption": "Partial_Upfront",
    "platform": "",
    "productDescription": "Linux/UNIX",
    "recommendedNormalizedUnitsToPurchase": "3",
    "recommendedNumberOfInstancesToPurchase": "5",
    "recurringStandardMonthlyCost": "353.74",
    "region": "Asia Pacific (Singapore)",
    "resourceType": "c6i",
    "service": "Elastic Compute Cloud (EC2)",
    "sizeFlexEligible": "false",
    "tenancy": "Shared",
    "term": "1 year",
    "upfrontCost": "173.01"
  },
  {
    "accountID": "665319725593",
    "accountName": "merrylion",
    "accountScope": "Linked",
    "availabilityZone": "",
    "averageNormalizedUnitsUsedPerHour": 426.9,
    "averageNumberOfInstancesUsedPerHour": 935.48,
    "averageUtilization": "6",
    "databaseEdition": "",
    "databaseEngine": "",
    "deploymentOption": "",
    "estimatedBreakEvenInMonths": "14.01",
    "estimatedMonthlyOnDemandCost": "113.32",
    "estimatedMonthlySavingsAmount": "263.85",
    "estimatedMonthlySavingsPercentage": "4",
    "estimatedReservationCostForLookbackPeriod": "44.79",
    "family": "r5",
    "instanceClass": "",
    "instanceSize": "",
    "instanceType": "r5.large",
    "licenseModel": "",
    "lookbackPeriodInDays": "7",
    "maximumNormalizedUnitsUsedPerHour": 27.74,
    "maximumNumberOfInstancesUsedPerHour": 8.33,
    "minimumNormalizedUnitsUsedPerHour": 57.66,
    "minimumNumberOfInstancesUsedPerHour": 34.08,
    "nodeType": "r5.large",
    "paymentOption": "Partial_Upfront",
    "platform": "",
    "productDescription": "Linux/UNIX",
    "recommendedNormalizedUnitsToPurchase": "4",
    "recommendedNumberOfInstancesToPurchase": "1",
    "recurringStandardMonthlyCost": "730.02",
    "region": "EU (Frankfurt)",
    "resourceType": "r5",
    "service": "Elastic Compute Cloud (EC2)",
    "sizeFlexEligible": "false",
    "tenancy": "Shared",
    "term": "1 year",
    "upfrontCost": "24.45"
  },
  {
    "accountID": "165283112664",
    "accountName": "quickparrot",
    "accountScope": "Linked",
    "availabilityZone": "",
    "averageNormalizedUnitsUsedPerHour": 664.71,
    "averageNumberOfInstancesUsedPerHour": 834.74,
    "averageUtilization": "82",
    "databaseEdition": "",
    "databaseEngine": "",
    "deploymentOption": "",
    "estimatedBreakEvenInMonths": "0.86",
    "estimatedMonthlyOnDemandCost": "2.44",
    "estimatedMonthlySavingsAmount": "189.10",
    "estimatedMonthlySavingsPercentage": "49",
    "estimatedReservationCostForLookbackPeriod": "11.04",
    "family": "t3",
    "instanceClass": "",
    "instanceSize": "",
    "instanceType": "t3.nano",
    "licenseModel": "",
    "lookbackPeriodInDays": "7",
    "maximumNormalizedUnitsUsedPerHour": 67.13,
    "maximumNumberOfInstancesUsedPerHour": 62.33,
    "minimumNormalizedUnitsUsedPerHour": 59.3,
    "minimumNumberOfInstancesUsedPerHour": 26.8,
    "nodeType": "t3.nano",
    "paymentOption": "Partial_Upfront",
    "platform": "",
    "productDescription": "Linux/UNIX",
    "recommendedNormalizedUnitsToPurchase": "7",
    "recommendedNumberOfInstancesToPurchase": "7",
    "recurringStandardMonthlyCost": "34.66",
    "region": "EU (Paris)",
    "resourceType": "t3",
    "service": "Elastic Compute Cloud (EC2)",
    "sizeFlexEligible": "false",
    "tenancy": "Shared",
    "term": "1 year",
    "upfrontCost": "368.62"
  },
  {
    "accountID": "620368136857",
    "accountName": "quickbear",
    "accountScope": "Linked",
    "availabilityZone": "",
    "averageNormalizedUnitsUsedPerHour": 570.92,
    "averageNumberOfInstancesUsedPerHour": 283.57,
    "averageUtilization": "71",
    "databaseEdition": "",
    "databaseEngine": "",
    "deploymentOption": "",
    "estimatedBreakEvenInMonths": "1.80",
    "estimatedMonthlyOnDemandCost": "171.81",
    "estimatedMonthlySavingsAmount": "163.50",
    "estimatedMonthlySavingsPercentage": "75",
    "estimatedReservationCostForLookbackPeriod": "28.72",
    "family": "t3",
    "instanceClass": "",
    "instanceSize": "",
    "instanceType": "t3.nano",
    "licenseModel": "",
    "lookbackPeriodInDays": "7",
    "maximumNormalizedUnitsUsedPerHour": 76.13,
    "maximumNumberOfInstancesUsedPerHour": 80.99,
    "minimumNormalizedUnitsUsedPerHour": 81,
    "minimumNumberOfInstancesUsedPerHour": 7.56,
    "nodeType": "t3.nano",
    "paymentOption": "Partial_Upfront",
    "platform": "",
    "productDescription": "Linux/UNIX",
    "recommendedNormalizedUnitsToPurchase": "7",
    "recommendedNumberOfInstancesToPurchase": "0",
    "recurringStandardMonthlyCost": "6.71",
    "region": "EU (London)",
    "resourceType": "t3",
    "service": "Elastic Compute Cloud (EC2)",
    "sizeFlexEligible": "false",
    "tenancy": "Shared",
    "term": "1 year",
    "upfrontCost": "547.40"
  },
  {
    "accountID": "165283112664",
    "accountName": "eagerurchin",
    "accountScope": "Linked",
    "availabilityZone": "",
    "averageNormalizedUnitsUsedPerHour": 309.33,
    "averageNumberOfInstancesUsedPerHour": 902.63,
    "averageUtilization": "78",
    "databaseEdition": "",
    "databaseEngine": "",
    "deploymentOption": "",
    "estimatedBreakEvenInMonths": "19.86",
    "estimatedMonthlyOnDemandCost": "145.67",
    "estimatedMonthlySavingsAmount": "122.61",
    "estimatedMonthlySavingsPercentage": "4",
    "estimatedReservationCostForLookbackPeriod": "83.56",
    "family": "g4dn",
    "instanceClass": "",
    "instanceSize": "",
    "instanceType": "g4dn.xlarge",
    "licenseModel": "",
    "lookbackPeriodInDays": "7",
    "maximumNormalizedUnitsUsedPerHour": 52.19,
    "maximumNumberOfInstancesUsedPerHour": 61.91,
    "minimumNormalizedUnitsUsedPerHour": 29.15,
    "minimumNumberOfInstancesUsedPerHour": 74.87,
    "nodeType": "g4dn.xlarge",
    "paymentOption": "Partial_Upfront",
    "platform": "",
    "productDescription": "Linux/UNIX",
    "recommendedNormalizedUnitsToPurchase": "3",
    "recommendedNumberOfInstancesToPurchase": "9",
    "recurringStandardMonthlyCost": "36.72",
    "region": "EU (Frankfurt)",
    "resourceType": "g4dn",
    "service": "Elastic Compute Cloud (EC2)",
    "sizeFlexEligible": "false",
    "tenancy": "Shared",
    "term": "1 year",
    "upfrontCost": "8.79"
  },
  {
    "accountID": "627286410625",
    "accountName": "excitedibis",
    "accountScope": "Linked",
    "availabilityZone": "",
    "averageNormalizedUnitsUsedPerHour": 532.9,
    "averageNumberOfInstancesUsedPerHour": 86.92,
    "averageUtilization": "80",
    "databaseEdition": "",
    "databaseEngine": "",
    "deploymentOption": "",
    "estimatedBreakEvenInMonths": "16.55",
    "estimatedMonthlyOnDemandCost": "21.15",
    "estimatedMonthlySavingsAmount": "385.96",
    "estimatedMonthlySavingsPercentage": "17",
    "estimatedReservationCostForLookbackPeriod": "1.75",
    "family": "c5a",
    "instanceClass": "",
    "instanceSize": "",
    "instanceType": "c5a.large",
    "licenseModel": "",
    "lookbackPeriodInDays": "7",
    "maximumNormalizedUnitsUsedPerHour": 64.45,
    "maximumNumberOfInstancesUsedPerHour": 19.28,
    "minimumNormalizedUnitsUsedPerHour": 79.24,
    "minimumNumberOfInstancesUsedPerHour": 0.41,
    "nodeType": "c5a.large",
    "paymentOption": "Partial_Upfront",
    "platform": "",
    "productDescription": "Linux/UNIX",
    "recommendedNormalizedUnitsToPurchase": "4",
    "recommendedNumberOfInstancesToPurchase": "5",
    "recurringStandardMonthlyCost": "422.36",
    "region": "EU (Ireland)",
    "resourceType": "c5a",
    "service": "Elastic Compute Cloud (EC2)",
    "sizeFlexEligible": "false",
    "tenancy": "Shared",
    "term": "1 year",
    "upfrontCost": "606.70"
  },
  {
    "accountID": "620368136857",
    "accountName": "quirkymouse",
    "accountScope": "Linked",
    "availabilityZone": "",
    "averageNormalizedUnitsUsedPerHour": 117.12,
    "averageNumberOfInstancesUsedPerHour": 259.43,
    "averageUtilization": "98",
    "databaseEdition": "",
    "databaseEngine": "",
    "deploymentOption": "",
    "estimatedBreakEvenInMonths": "7.72",
    "estimatedMonthlyOnDemandCost": "200.19",
    "estimatedMonthlySavingsAmount": "38.47",
    "estimatedMonthlySavingsPercentage": "16",
    "estimatedReservationCostForLookbackPeriod": "2.05",
    "family": "c5",
    "instanceClass": "",
    "instanceSize": "",
    "instanceType": "c5.xlarge",
    "licenseModel": "",
    "lookbackPeriodInDays": "7",
    "maximumNormalizedUnitsUsedPerHour": 73.52,
    "maximumNumberOfInstancesUsedPerHour": 37.13,
    "minimumNormalizedUnitsUsedPerHour": 46.1,
    "minimumNumberOfInstancesUsedPerHour": 79.08,
    "nodeType": "c5.xlarge",
    "paymentOption": "Partial_Upfront",
    "platform": "",
    "productDescription": "Linux/UNIX",
    "recommendedNormalizedUnitsToPurchase": "4",
    "recommendedNumberOfInstancesToPurchase": "4",
    "recurringStandardMonthlyCost": "141.68",
    "region": "EU (Paris)",
    "resourceType": "c5",
    "service": "Elastic Compute Cloud (EC2)",
    "sizeFlexEligible": "false",
    "tenancy": "Shared",
    "term": "1 year",
    "upfrontCost": "480.07"
  },
  {
    "accountID": "627286410625",
    "accountName": "fierceowl",
    "accountScope": "Linked",
    "availabilityZone": "",
    "averageNormalizedUnitsUsedPerHour": 810.3,
    "averageNumberOfInstancesUsedPerHour": 614.96,
    "averageUtilization": "43",
    "databaseEdition": "",
    "databaseEngine": "",
    "deploymentOption": "",
    "estimatedBreakEvenInMonths": "13.93",
    "estimatedMonthlyOnDemandCost": "194.95",
    "estimatedMonthlySavingsAmount": "700.20",
    "estimatedMonthlySavingsPercentage": "62",
    "estimatedReservationCostForLookbackPeriod": "3.42",
    "family": "c6i",
    "instanceClass": "",
    "instanceSize": "",
    "instanceType": "c6i.large",
    "licenseModel": "",
    "lookbackPeriodInDays": "7",
    "maximumNormalizedUnitsUsedPerHour": 5.37,
    "maximumNumberOfInstancesUsedPerHour": 11.87,
    "minimumNormalizedUnitsUsedPerHour": 3.61,
    "minimumNumberOfInstancesUsedPerHour": 41.61,
    "nodeType": "c6i.large",
    "paymentOption": "Partial_Upfront",
    "platform": "",
    "productDescription": "Linux/UNIX",
    "recommendedNormalizedUnitsToPurchase": "5",
    "recommendedNumberOfInstancesToPurchase": "2",
    "recurringStandardMonthlyCost": "77.09",
    "region": "Asia Pacific (Tokyo)",
    "resourceType": "c6i",
    "service": "Elastic Compute Cloud (EC2)",
    "sizeFlexEligible": "false",
    "tenancy": "Shared",
    "term": "1 year",
    "upfrontCost": "128.77"
  },
  {
    "accountID": "138186646095",
    "accountName": "jovialmouse",
    "accountScope": "Linked",
    "availabilityZone": "",
    "averageNormalizedUnitsUsedPerHour": 141.23,
    "averageNumberOfInstancesUsedPerHour": 744.89,
    "averageUtilization": "7",
    "databaseEdition": "",
    "databaseEngine": "",
    "deploymentOption": "",
    "estimatedBreakEvenInMonths": "18.65",
    "estimatedMonthlyOnDemandCost": "217.35",
    "estimatedMonthlySavingsAmount": "595.94",
    "estimatedMonthlySavingsPercentage": "74",
    "estimatedReservationCostForLookbackPeriod": "80.98",
    "family": "c6i",
    "instanceClass": "",
    "instanceSize": "",
    "instanceType": "c6i.large",
    "licenseModel": "",
    "lookbackPeriodInDays": "7",
    "maximumNormalizedUnitsUsedPerHour": 13.24,
    "maximumNumberOfInstancesUsedPerHour": 32.86,
    "minimumNormalizedUnitsUsedPerHour": 43.51,
    "minimumNumberOfInstancesUsedPerHour": 34.71,
    "nodeType": "c6i.large",
    "paymentOption": "Partial_Upfront",
    "platform": "",
    "productDescription": "Linux/UNIX",
    "recommendedNormalizedUnitsToPurchase": "5",
    "recommendedNumberOfInstancesToPurchase": "1",
    "recurringStandardMonthlyCost": "263.07",
    "region": "Asia Pacific (Tokyo)",
    "resourceType": "c6i",
    "service": "Elastic Compute Cloud (EC2)",
    "sizeFlexEligible": "false",
    "tenancy": "Shared",
    "term": "1 year",
    "upfrontCost": "27.55"
  },
  {
    "accountID": "353197488767",
    "accountName": "fiercewhale",
    "accountScope": "Linked",
    "availabilityZone": "",
    "averageNormalizedUnitsUsedPerHour": 501.08,
    "averageNumberOfInstancesUsedPerHour": 385.66,
    "averageUtilization": "81",
    "databaseEdition": "",
    "databaseEngine": "",
    "deploymentOption": "",
    "estimatedBreakEvenInMonths": "0.07",
    "estimatedMonthlyOnDemandCost": "49.88",
    "estimatedMonthlySavingsAmount": "28.43",
    "estimatedMonthlySavingsPercentage": "46",
    "estimatedReservationCostForLookbackPeriod": "4.89",
    "family": "m5",
    "instanceClass": "",
    "instanceSize": "",
    "instanceType": "m5.large",
    "licenseModel": "",
    "lookbackPeriodInDays": "7",
    "maximumNormalizedUnitsUsedPerHour": 91.11,
    "maximumNumberOfInstancesUsedPerHour": 64.85,
    "minimumNormalizedUnitsUsedPerHour": 41.17,
    "minimumNumberOfInstancesUsedPerHour": 68.21,
    "nodeType": "m5.large",
    "paymentOption": "Partial_Upfront",
    "platform": "",
    "productDescription": "Linux/UNIX",
    "recommendedNormalizedUnitsToPurchase": "9",
    "recommendedNumberOfInstancesToPurchase": "1",
    "recurringStandardMonthlyCost": "480.36",
    "region": "US West (Oregon)",
    "resourceType": "m5",
    "service": "Elastic Compute Cloud (EC2)",
    "sizeFlexEligible": "false",
    "tenancy": "Shared",
    "term": "1 year",
    "upfrontCost": "162.08"
  },
  {
    "accountID": "925894598672",
    "accountName": "quirkyrabbit",
    "accountScope": "Linked",
    "availabilityZone": "",
    "averageNormalizedUnitsUsedPerHour": 864.69,
    "averageNumberOfInstancesUsedPerHour": 653.89,
    "averageUtilization": "63",
    "databaseEdition": "",
    "databaseEngine": "",
    "deploymentOption": "",
    "estimatedBreakEvenInMonths": "48.59",
    "estimatedMonthlyOnDemandCost": "58.23",
    "estimatedMonthlySavingsAmount": "10.46",
    "estimatedMonthlySavingsPercentage": "90",
    "estimatedReservationCostForLookbackPeriod": "17.69",
    "family": "r5",
    "instanceClass": "",
    "instanceSize": "",
    "instanceType": "r5.large",
    "licenseModel": "",
    "lookbackPeriodInDays": "7",
    "maximumNormalizedUnitsUsedPerHour": 51.79,
    "maximumNumberOfInstancesUsedPerHour": 4.36,
    "minimumNormalizedUnitsUsedPerHour": 40.36,
    "minimumNumberOfInstancesUsedPerHour": 60.97,
    "nodeType": "r5.large",
    "paymentOption": "Partial_Upfront",
    "platform": "",
    "productDescription": "Linux/UNIX",
    "recommendedNormalizedUnitsToPurchase": "4",
    "recommendedNumberOfInstancesToPurchase": "6",
    "recurringStandardMonthlyCost": "328.02",
    "region": "EU (London)",
    "resourceType": "r5",
    "service": "Elastic Compute Cloud (EC2)",
    "sizeFlexEligible": "false",
    "tenancy": "Shared",
    "term": "1 year",
    "upfrontCost": "644.16"
  },
  {
    "accountID": "646728909564",
    "accountName": "calmcat",
    "accountScope": "Linked",
    "availabilityZone": "",
    "averageNormalizedUnitsUsedPerHour": 523.6,
    "averageNumberOfInstancesUsedPerHour": 320.02,
    "averageUtilization": "93",
    "databaseEdition": "",
    "databaseEngine": "",
    "deploymentOption": "",
    "estimatedBreakEvenInMonths": "5.00",
    "estimatedMonthlyOnDemandCost": "242.13",
    "estimatedMonthlySavingsAmount": "103.89",
    "estimatedMonthlySavingsPercentage": "44",
    "estimatedReservationCostForLookbackPeriod": "0.23",
    "family": "r5",
    "instanceClass": "",
    "instanceSize": "",
    "instanceType": "r5.large",
    "licenseModel": "",
    "lookbackPeriodInDays": "7",
    "maximumNormalizedUnitsUsedPerHour": 55.2,
    "maximumNumberOfInstancesUsedPerHour": 90.33,
    "minimumNormalizedUnitsUsedPerHour": 0.72,
    "minimumNumberOfInstancesUsedPerHour": 62.19,
    "nodeType": "r5.large",
    "paymentOption": "Partial_Upfront",
    "platform": "",
    "productDescription": "Linux/UNIX",
    "recommendedNormalizedUnitsToPurchase": "9",
    "recommendedNumberOfInstancesToPurchase": "5",
    "recurringStandardMonthlyCost": "319.65",
    "region": "EU (Ireland)",
    "resourceType": "r5",
    "service": "Elastic Compute Cloud (EC2)",
    "sizeFlexEligible": "false",
    "tenancy": "Shared",
    "term": "1 year",
    "upfrontCost": "646.37"
  },
  {
    "accountID": "138186646095",
    "accountName": "adventurousurchin",
    "accountScope": "Linked",
    "availabilityZone": "",
    "averageNormalizedUnitsUsedPerHour": 712.57,
    "averageNumberOfInstancesUsedPerHour": 231.21,
    "averageUtilization": "74",
    "databaseEdition": "",
    "databaseEngine": "",
    "deploymentOption": "",
    "estimatedBreakEvenInMonths": "67.01",
    "estimatedMonthlyOnDemandCost": "29.92",
    "estimatedMonthlySavingsAmount": "25.98",
    "estimatedMonthlySavingsPercentage": "40",
    "estimatedReservationCostForLookbackPeriod": "57.34",
    "family": "c5",
    "instanceClass": "",
    "instanceSize": "",
    "instanceType": "c5.xlarge",
    "licenseModel": "",
    "lookbackPeriodInDays": "7",
    "maximumNormalizedUnitsUsedPerHour": 31.04,
    "maximumNumberOfInstancesUsedPerHour": 8.14,
    "minimumNormalizedUnitsUsedPerHour": 33.39,
    "minimumNumberOfInstancesUsedPerHour": 76.83,
    "nodeType": "c5.xlarge",
    "paymentOption": "Partial_Upfront",
    "platform": "",
    "productDescription": "Linux/UNIX",
    "recommendedNormalizedUnitsToPurchase": "3",
    "recommendedNumberOfInstancesToPurchase": "8",
    "recurringStandardMonthlyCost": "192.60",
    "region": "EU (Ireland)",
    "resourceType": "c5",
    "service": "Elastic Compute Cloud (EC2)",
    "sizeFlexEligible": "false",
    "tenancy": "Shared",
    "term": "1 year",
    "upfrontCost": "91.60"
  },
  {
    "accountID": "353197488767",
    "accountName": "nervousgiraffe",
    "accountScope": "Linked",
    "availabilityZone": "",
    "averageNormalizedUnitsUsedPerHour": 311.31,
    "averageNumberOfInstancesUsedPerHour": 536.37,
    "averageUtilization": "82",
    "databaseEdition": "",
    "databaseEngine": "",
    "deploymentOption": "",
    "estimatedBreakEvenInMonths": "38.85",
    "estimatedMonthlyOnDemandCost": "166.12",
    "estimatedMonthlySavingsAmount": "300.28",
    "estimatedMonthlySavingsPercentage": "49",
    "estimatedReservationCostForLookbackPeriod": "35.49",
    "family": "t2",
    "instanceClass": "",
    "instanceSize": "",
    "instanceType": "t2.nano",
    "licenseModel": "",
    "lookbackPeriodInDays": "7",
    "maximumNormalizedUnitsUsedPerHour": 89.35,
    "maximumNumberOfInstancesUsedPerHour": 81.57,
    "minimumNormalizedUnitsUsedPerHour": 51.8,
    "minimumNumberOfInstancesUsedPerHour": 44.55,
    "nodeType": "t2.nano",
    "paymentOption": "Partial_Upfront",
    "platform": "",
    "productDescription": "Linux/UNIX",
    "recommendedNormalizedUnitsToPurchase": "1",
    "recommendedNumberOfInstancesToPurchase": "1",
    "recurringStandardMonthlyCost": "25.32",
    "region": "EU (Ireland)",
    "resourceType": "t2",
    "service": "Elastic Compute Cloud (EC2)",
    "sizeFlexEligible": "false",
    "tenancy": "Shared",
    "term": "1 year",
    "upfrontCost": "641.12"
  },
  {
    "accountID": "138186646095",
    "accountName": "lazynewt",
    "accountScope": "Linked",
    "availabilityZone": "",
    "averageNormalizedUnitsUsedPerHour": 705,
    "averageNumberOfInstancesUsedPerHour": 794.08,
    "averageUtilization": "35",
    "databaseEdition": "",
    "databaseEngine": "",
    "deploymentOption": "",
    "estimatedBreakEvenInMonths": "11.70",
    "estimatedMonthlyOnDemandCost": "286.97",
    "estimatedMonthlySavingsAmount": "2.06",
    "estimatedMonthlySavingsPercentage": "90",
    "estimatedReservationCostForLookbackPeriod": "61.09",
    "family": "c5a",
    "instanceClass": "",
    "instanceSize": "",
    "instanceType": "c5a.large",
    "licenseModel": "",
    "lookbackPeriodInDays": "7",
    "maximumNormalizedUnitsUsedPerHour": 75.69,
    "maximumNumberOfInstancesUsedPerHour": 55.86,
    "minimumNormalizedUnitsUsedPerHour": 77.19,
    "minimumNumberOfInstancesUsedPerHour": 46.28,
    "nodeType": "c5a.large",
    "paymentOption": "Partial_Upfront",
    "platform": "",
    "productDescription": "Linux/UNIX",
    "recommendedNormalizedUnitsToPurchase": "8",
    "recommendedNumberOfInstancesToPurchase": "8",
    "recurringStandardMonthlyCost": "53.23",
    "region": "Asia Pacific (Sydney)",
    "resourceType": "c5a",
    "service": "Elastic Compute Cloud (EC2)",
    "sizeFlexEligible": "false",
    "tenancy": "Shared",
    "term": "1 year",
    "upfrontCost": "64.95"
  },
  {
    "accountID": "620368136857",
    "accountName": "upbeatbear",
    "accountScope": "Linked",
    "availabilityZone": "",
    "averageNormalizedUnitsUsedPerHour": 802.63,
    "averageNumberOfInstancesUsedPerHour": 765.7,
    "averageUtilization": "69",
    "databaseEdition": "",
    "databaseEngine": "",
    "deploymentOption": "",
    "estimatedBreakEvenInMonths": "23.70",
    "estimatedMonthlyOnDemandCost": "339.76",
    "estimatedMonthlySavingsAmount": "84.65",
    "estimatedMonthlySavingsPercentage": "63",
    "estimatedReservationCostForLookbackPeriod": "2.96",
    "family": "i4i",
    "instanceClass": "",
    "instanceSize": "",
    "instanceType": "i4i.large",
    "licenseModel": "",
    "lookbackPeriodInDays": "7",
    "maximumNormalizedUnitsUsedPerHour": 95.9,
    "maximumNumberOfInstancesUsedPerHour": 86.21,
    "minimumNormalizedUnitsUsedPerHour": 60.8,
    "minimumNumberOfInstancesUsedPerHour": 70.08,
    "nodeType": "i4i.large",
    "paymentOption": "Partial_Upfront",
    "platform": "",
    "productDescription": "Linux/UNIX",
    "recommendedNormalizedUnitsToPurchase": "8",
    "recommendedNumberOfInstancesToPurchase": "7",
    "recurringStandardMonthlyCost": "748.96",
    "region": "EU (Ireland)",
    "resourceType": "i4i",
    "service": "Elastic Compute Cloud (EC2)",
    "sizeFlexEligible": "false",
    "tenancy": "Shared",
    "term": "1 year",
    "upfrontCost": "774.58"
  },
  {
    "accountID": "999773517191",
    "accountName": "proudeel",
    "accountScope": "Linked",
    "availabilityZone": "",
    "averageNormalizedUnitsUsedPerHour": 382.53,
    "averageNumberOfInstancesUsedPerHour": 847.33,
    "averageUtilization": "14",
    "databaseEdition": "",
    "databaseEngine": "",
    "deploymentOption": "",
    "estimatedBreakEvenInMonths": "16.65",
    "estimatedMonthlyOnDemandCost": "2.13",
    "estimatedMonthlySavingsAmount": "10.53",
    "estimatedMonthlySavingsPercentage": "94",
    "estimatedReservationCostForLookbackPeriod": "51.81",
    "family": "c5a",
    "instanceClass": "",
    "instanceSize": "",
    "instanceType": "c5a.large",
    "licenseModel": "",
    "lookbackPeriodInDays": "7",
    "maximumNormalizedUnitsUsedPerHour": 21.77,
    "maximumNumberOfInstancesUsedPerHour": 95.27,
    "minimumNormalizedUnitsUsedPerHour": 71.73,
    "minimumNumberOfInstancesUsedPerHour": 17.17,
    "nodeType": "c5a.large",
    "paymentOption": "Partial_Upfront",
    "platform": "",
    "productDescription": "Linux/UNIX",
    "recommendedNormalizedUnitsToPurchase": "6",
    "recommendedNumberOfInstancesToPurchase": "3",
    "recurringStandardMonthlyCost": "23.36",
    "region": "EU (London)",
    "resourceType": "c5a",
    "service": "Elastic Compute Cloud (EC2)",
    "sizeFlexEligible": "false",
    "tenancy": "Shared",
    "term": "1 year",
    "upfrontCost": "17.82"
  },
  {
    "accountID": "646728909564",
    "accountName": "excitedzebra",
    "accountScope": "Linked",
    "availabilityZone": "",
    "averageNormalizedUnitsUsedPerHour": 800.29,
    "averageNumberOfInstancesUsedPerHour": 958.05,
    "averageUtilization": "45",
    "databaseEdition": "",
    "databaseEngine": "",
    "deploymentOption": "",
    "estimatedBreakEvenInMonths": "18.03",
    "estimatedMonthlyOnDemandCost": "127.71",
    "estimatedMonthlySavingsAmount": "105.46",
    "estimatedMonthlySavingsPercentage": "19",
    "estimatedReservationCostForLookbackPeriod": "46.91",
    "family": "c4",
    "instanceClass": "",
    "instanceSize": "",
    "instanceType": "c4.large",
    "licenseModel": "",
    "lookbackPeriodInDays": "7",
    "maximumNormalizedUnitsUsedPerHour": 41.34,
    "maximumNumberOfInstancesUsedPerHour": 98.07,
    "minimumNormalizedUnitsUsedPerHour": 33.2,
    "minimumNumberOfInstancesUsedPerHour": 42.96,
    "nodeType": "c4.large",
    "paymentOption": "Partial_Upfront",
    "platform": "",
    "productDescription": "Linux/UNIX",
    "recommendedNormalizedUnitsToPurchase": "0",
    "recommendedNumberOfInstancesToPurchase": "4",
    "recurringStandardMonthlyCost": "116.71",
    "region": "Asia Pacific (Tokyo)",
    "resourceType": "c4",
    "service": "Elastic Compute Cloud (EC2)",
    "sizeFlexEligible": "false",
    "tenancy": "Shared",
    "term": "1 year",
    "upfrontCost": "199.72"
  },
  {
    "accountID": "646728909564",
    "accountName": "braveelephant",
    "accountScope": "Linked",
    "availabilityZone": "",
    "averageNormalizedUnitsUsedPerHour": 573.79,
    "averageNumberOfInstancesUsedPerHour": 908.79,
    "averageUtilization": "47",
    "databaseEdition": "",
    "databaseEngine": "",
    "deploymentOption": "",
    "estimatedBreakEvenInMonths": "17.11",
    "estimatedMonthlyOnDemandCost": "368.25",
    "estimatedMonthlySavingsAmount": "8.03",
    "estimatedMonthlySavingsPercentage": "41",
    "estimatedReservationCostForLookbackPeriod": "34.45",
    "family": "c5",
    "instanceClass": "",
    "instanceSize": "",
    "instanceType": "c5.xlarge",
    "licenseModel": "",
    "lookbackPeriodInDays": "7",
    "maximumNormalizedUnitsUsedPerHour": 14.81,
    "maximumNumberOfInstancesUsedPerHour": 19.82,
    "minimumNormalizedUnitsUsedPerHour": 62.61,
    "minimumNumberOfInstancesUsedPerHour": 55.75,
    "nodeType": "c5.xlarge",
    "paymentOption": "Partial_Upfront",
    "platform": "",
    "productDescription": "Linux/UNIX",
    "recommendedNormalizedUnitsToPurchase": "8",
    "recommendedNumberOfInstancesToPurchase": "8",
    "recurringStandardMonthlyCost": "25.69",
    "region": "EU (Frankfurt)",
    "resourceType": "c5",
    "service": "Elastic Compute Cloud (EC2)",
    "sizeFlexEligible": "false",
    "tenancy": "Shared",
    "term": "1 year",
    "upfrontCost": "202.47"
  }
]
